{
  "CatalogTitle": "iwacu   le magazine ",
  "OriginalTitle": "Iwacu : le magazine.",
  "CallNumber": "DT450.5 .I93",
  "Issues": [
    {
      "Identifier": "8| 2.1\n        a| 14\n        i| 2013\n        j| 03",
      "Parts": [
        {
          "Key": "8",
          "Value": " 2.1"
        },
        {
          "Key": "a",
          "Value": " 14"
        },
        {
          "Key": "i",
          "Value": " 2013"
        },
        {
          "Key": "j",
          "Value": " 03"
        }
      ],
      "Timestamp": "2015-12-03T05:45:47.0493947-08:00",
      "Signature": 1788211279
    },
    {
      "Identifier": "8| 2.2\n        a| 15\n        i| 2013\n        j| 04",
      "Parts": [
        {
          "Key": "8",
          "Value": " 2.2"
        },
        {
          "Key": "a",
          "Value": " 15"
        },
        {
          "Key": "i",
          "Value": " 2013"
        },
        {
          "Key": "j",
          "Value": " 04"
        }
      ],
      "Timestamp": "2016-03-11T03:00:01.4181953-08:00",
      "Signature": -221046479
    },
    {
      "Identifier": "8| 2.3\n        a| 16\n        i| 2013\n        j| 05",
      "Parts": [
        {
          "Key": "8",
          "Value": " 2.3"
        },
        {
          "Key": "a",
          "Value": " 16"
        },
        {
          "Key": "i",
          "Value": " 2013"
        },
        {
          "Key": "j",
          "Value": " 05"
        }
      ],
      "Timestamp": "2016-03-11T03:00:01.4181953-08:00",
      "Signature": -101378609
    },
    {
      "Identifier": "8| 2.4\n        a| 17\n        i| 2013\n        j| 06",
      "Parts": [
        {
          "Key": "8",
          "Value": " 2.4"
        },
        {
          "Key": "a",
          "Value": " 17"
        },
        {
          "Key": "i",
          "Value": " 2013"
        },
        {
          "Key": "j",
          "Value": " 06"
        }
      ],
      "Timestamp": "2016-03-11T03:00:01.4181953-08:00",
      "Signature": -141267899
    },
    {
      "Identifier": "8| 3.1\n        a| 1\n        i| 2011\n        j| 11",
      "Parts": [
        {
          "Key": "8",
          "Value": " 3.1"
        },
        {
          "Key": "a",
          "Value": " 1"
        },
        {
          "Key": "i",
          "Value": " 2011"
        },
        {
          "Key": "j",
          "Value": " 11"
        }
      ],
      "Timestamp": "2016-03-11T03:00:01.4181953-08:00",
      "Signature": -212254521
    },
    {
      "Identifier": "8| 3.2\n        a| 2\n        i| 2011",
      "Parts": [
        {
          "Key": "8",
          "Value": " 3.2"
        },
        {
          "Key": "a",
          "Value": " 2"
        },
        {
          "Key": "i",
          "Value": " 2011"
        }
      ],
      "Timestamp": "2016-03-11T03:00:01.4181953-08:00",
      "Signature": 2069787401
    },
    {
      "Identifier": "8| 3.3\n        a| 3\n        i| 2012\n        j| 01",
      "Parts": [
        {
          "Key": "8",
          "Value": " 3.3"
        },
        {
          "Key": "a",
          "Value": " 3"
        },
        {
          "Key": "i",
          "Value": " 2012"
        },
        {
          "Key": "j",
          "Value": " 01"
        }
      ],
      "Timestamp": "2016-03-11T03:00:01.4181953-08:00",
      "Signature": 48292597
    },
    {
      "Identifier": "8| 3.4\n        a| 4\n        i| 2012\n        j| 03",
      "Parts": [
        {
          "Key": "8",
          "Value": " 3.4"
        },
        {
          "Key": "a",
          "Value": " 4"
        },
        {
          "Key": "i",
          "Value": " 2012"
        },
        {
          "Key": "j",
          "Value": " 03"
        }
      ],
      "Timestamp": "2016-03-11T03:00:01.4181953-08:00",
      "Signature": 119923445
    },
    {
      "Identifier": "8| 3.5\n        a| 6\n        i| 2012\n        j| 05",
      "Parts": [
        {
          "Key": "8",
          "Value": " 3.5"
        },
        {
          "Key": "a",
          "Value": " 6"
        },
        {
          "Key": "i",
          "Value": " 2012"
        },
        {
          "Key": "j",
          "Value": " 05"
        }
      ],
      "Timestamp": "2016-03-11T03:00:01.4181953-08:00",
      "Signature": -23207180
    },
    {
      "Identifier": "8| 3.6\n        a| 7\n        i| 2012\n        j| 06",
      "Parts": [
        {
          "Key": "8",
          "Value": " 3.6"
        },
        {
          "Key": "a",
          "Value": " 7"
        },
        {
          "Key": "i",
          "Value": " 2012"
        },
        {
          "Key": "j",
          "Value": " 06"
        }
      ],
      "Timestamp": "2016-03-11T03:00:01.4181953-08:00",
      "Signature": -236985612
    },
    {
      "Identifier": "8| 3.7\n        a| 8\n        i| 2012\n        j| 07",
      "Parts": [
        {
          "Key": "8",
          "Value": " 3.7"
        },
        {
          "Key": "a",
          "Value": " 8"
        },
        {
          "Key": "i",
          "Value": " 2012"
        },
        {
          "Key": "j",
          "Value": " 07"
        }
      ],
      "Timestamp": "2016-03-11T03:00:01.4181953-08:00",
      "Signature": 908976885
    },
    {
      "Identifier": "8| 3.8\n        a| 9\n        i| 2012\n        j| 08",
      "Parts": [
        {
          "Key": "8",
          "Value": " 3.8"
        },
        {
          "Key": "a",
          "Value": " 9"
        },
        {
          "Key": "i",
          "Value": " 2012"
        },
        {
          "Key": "j",
          "Value": " 08"
        }
      ],
      "Timestamp": "2016-03-11T03:00:01.4181953-08:00",
      "Signature": 695460597
    },
    {
      "Identifier": "8| 3.9\n        a| 10\n        i| 2012\n        j| 09",
      "Parts": [
        {
          "Key": "8",
          "Value": " 3.9"
        },
        {
          "Key": "a",
          "Value": " 10"
        },
        {
          "Key": "i",
          "Value": " 2012"
        },
        {
          "Key": "j",
          "Value": " 09"
        }
      ],
      "Timestamp": "2016-03-11T03:00:01.4181953-08:00",
      "Signature": 599744753
    },
    {
      "Identifier": "8| 3.10\n        a| 11\n        i| 2012\n        j| 12",
      "Parts": [
        {
          "Key": "8",
          "Value": " 3.10"
        },
        {
          "Key": "a",
          "Value": " 11"
        },
        {
          "Key": "i",
          "Value": " 2012"
        },
        {
          "Key": "j",
          "Value": " 12"
        }
      ],
      "Timestamp": "2016-03-11T03:00:01.4181953-08:00",
      "Signature": -2121908189
    },
    {
      "Identifier": "8| 3.11\n        a| 12\n        i| 2013\n        j| 01",
      "Parts": [
        {
          "Key": "8",
          "Value": " 3.11"
        },
        {
          "Key": "a",
          "Value": " 12"
        },
        {
          "Key": "i",
          "Value": " 2013"
        },
        {
          "Key": "j",
          "Value": " 01"
        }
      ],
      "Timestamp": "2016-03-11T03:00:01.4181953-08:00",
      "Signature": -617166129
    },
    {
      "Identifier": "8| 3.12\n        a| 13\n        i| 2013\n        j| 02",
      "Parts": [
        {
          "Key": "8",
          "Value": " 3.12"
        },
        {
          "Key": "a",
          "Value": " 13"
        },
        {
          "Key": "i",
          "Value": " 2013"
        },
        {
          "Key": "j",
          "Value": " 02"
        }
      ],
      "Timestamp": "2016-03-11T03:00:01.4181953-08:00",
      "Signature": -657055419
    },
    {
      "Identifier": "8| 3.13\n        a| 18\n        i| 2013\n        j| 07/08",
      "Parts": [
        {
          "Key": "8",
          "Value": " 3.13"
        },
        {
          "Key": "a",
          "Value": " 18"
        },
        {
          "Key": "i",
          "Value": " 2013"
        },
        {
          "Key": "j",
          "Value": " 07/08"
        }
      ],
      "Timestamp": "2016-03-11T03:00:01.4181953-08:00",
      "Signature": -476331683
    },
    {
      "Identifier": "8| 3.14\n        a| 19\n        i| 2013\n        j| 09/10",
      "Parts": [
        {
          "Key": "8",
          "Value": " 3.14"
        },
        {
          "Key": "a",
          "Value": " 19"
        },
        {
          "Key": "i",
          "Value": " 2013"
        },
        {
          "Key": "j",
          "Value": " 09/10"
        }
      ],
      "Timestamp": "2016-03-11T03:00:01.4181953-08:00",
      "Signature": -113460733
    },
    {
      "Identifier": "8| 3.15\n        a| 20\n        i| 2013\n        j| 11/12",
      "Parts": [
        {
          "Key": "8",
          "Value": " 3.15"
        },
        {
          "Key": "a",
          "Value": " 20"
        },
        {
          "Key": "i",
          "Value": " 2013"
        },
        {
          "Key": "j",
          "Value": " 11/12"
        }
      ],
      "Timestamp": "2016-03-11T03:00:01.4181953-08:00",
      "Signature": -339588137
    },
    {
      "Identifier": "8| 3.16\n        a| 21\n        i| 2014\n        j| 01/02",
      "Parts": [
        {
          "Key": "8",
          "Value": " 3.16"
        },
        {
          "Key": "a",
          "Value": " 21"
        },
        {
          "Key": "i",
          "Value": " 2014"
        },
        {
          "Key": "j",
          "Value": " 01/02"
        }
      ],
      "Timestamp": "2016-03-11T03:00:01.4181953-08:00",
      "Signature": 2091527603
    },
    {
      "Identifier": "8| 3.17\n        a| 22\n        i| 2014\n        j| 03",
      "Parts": [
        {
          "Key": "8",
          "Value": " 3.17"
        },
        {
          "Key": "a",
          "Value": " 22"
        },
        {
          "Key": "i",
          "Value": " 2014"
        },
        {
          "Key": "j",
          "Value": " 03"
        }
      ],
      "Timestamp": "2016-03-11T03:00:01.4181953-08:00",
      "Signature": 1014346757
    },
    {
      "Identifier": "8| 3.18\n        a| 23\n        i| 2014\n        j| 04",
      "Parts": [
        {
          "Key": "8",
          "Value": " 3.18"
        },
        {
          "Key": "a",
          "Value": " 23"
        },
        {
          "Key": "i",
          "Value": " 2014"
        },
        {
          "Key": "j",
          "Value": " 04"
        }
      ],
      "Timestamp": "2016-03-11T03:00:01.4181953-08:00",
      "Signature": 974457467
    },
    {
      "Identifier": "8| 3.19\n        a| 24\n        i| 2014\n        j| 05/06",
      "Parts": [
        {
          "Key": "8",
          "Value": " 3.19"
        },
        {
          "Key": "a",
          "Value": " 24"
        },
        {
          "Key": "i",
          "Value": " 2014"
        },
        {
          "Key": "j",
          "Value": " 05/06"
        }
      ],
      "Timestamp": "2016-03-11T03:00:01.4181953-08:00",
      "Signature": 1437088688
    },
    {
      "Identifier": "8| 3.20\n        a| 25\n        i| 2014\n        j| 07",
      "Parts": [
        {
          "Key": "8",
          "Value": " 3.20"
        },
        {
          "Key": "a",
          "Value": " 25"
        },
        {
          "Key": "i",
          "Value": " 2014"
        },
        {
          "Key": "j",
          "Value": " 07"
        }
      ],
      "Timestamp": "2016-03-11T03:00:01.4181953-08:00",
      "Signature": 1813750934
    },
    {
      "Identifier": "8| 3.21\n        a| 26\n        i| 2014\n        j| 08",
      "Parts": [
        {
          "Key": "8",
          "Value": " 3.21"
        },
        {
          "Key": "a",
          "Value": " 26"
        },
        {
          "Key": "i",
          "Value": " 2014"
        },
        {
          "Key": "j",
          "Value": " 08"
        }
      ],
      "Timestamp": "2016-03-11T03:00:01.4181953-08:00",
      "Signature": 770619390
    },
    {
      "Identifier": "8| 3.22\n        a| 27\n        i| 2014\n        j| 09",
      "Parts": [
        {
          "Key": "8",
          "Value": " 3.22"
        },
        {
          "Key": "a",
          "Value": " 27"
        },
        {
          "Key": "i",
          "Value": " 2014"
        },
        {
          "Key": "j",
          "Value": " 09"
        }
      ],
      "Timestamp": "2016-03-11T03:00:01.4181953-08:00",
      "Signature": -432069314
    },
    {
      "Identifier": "8| 3.23\n        a| 29\n        i| 2015\n        j| 01",
      "Parts": [
        {
          "Key": "8",
          "Value": " 3.23"
        },
        {
          "Key": "a",
          "Value": " 29"
        },
        {
          "Key": "i",
          "Value": " 2015"
        },
        {
          "Key": "j",
          "Value": " 01"
        }
      ],
      "Timestamp": "2016-03-11T03:00:01.4181953-08:00",
      "Signature": -1064317156
    },
    {
      "Identifier": "8| 3.24\n        a| 30\n        i| 2015\n        j| 09",
      "Parts": [
        {
          "Key": "8",
          "Value": " 3.24"
        },
        {
          "Key": "a",
          "Value": " 30"
        },
        {
          "Key": "i",
          "Value": " 2015"
        },
        {
          "Key": "j",
          "Value": " 09"
        }
      ],
      "Timestamp": "2016-03-11T03:00:01.4181953-08:00",
      "Signature": 590897393
    },
    {
      "Identifier": "8| 3.25\n        a| 31\n        i| 2015\n        j| 10/11",
      "Parts": [
        {
          "Key": "8",
          "Value": " 3.25"
        },
        {
          "Key": "a",
          "Value": " 31"
        },
        {
          "Key": "i",
          "Value": " 2015"
        },
        {
          "Key": "j",
          "Value": " 10/11"
        }
      ],
      "Timestamp": "2016-03-11T03:00:01.4181953-08:00",
      "Signature": 1165932821
    }
  ],
  "StanfordLibraryId": 10292732,
  "OriginalExcelRow": null,
  "Libraries": [
    "GREEN|CURRENTPER"
  ],
  "LastUpdatedTimestamp": "2016-03-11T03:00:01.4181953-08:00",
  "PublicationPatterns": [
    {
      "Parts": [
        {
          "Key": "8",
          "Value": " 2"
        },
        {
          "Key": "a",
          "Value": " no"
        },
        {
          "Key": "i",
          "Value": " (year)"
        },
        {
          "Key": "j",
          "Value": " (month)"
        }
      ]
    },
    {
      "Parts": [
        {
          "Key": "8",
          "Value": " 3"
        },
        {
          "Key": "a",
          "Value": " no."
        },
        {
          "Key": "i",
          "Value": " (year)"
        },
        {
          "Key": "j",
          "Value": " (month)"
        }
      ]
    }
  ],
  "PublicationFrequency": [
    "Monthly"
  ]
}